pybdynamics/__init__.py
pybdynamics/initialize.py
pybdynamics/nlist.py
pybdynamics/pbc.py
pybdynamics/potentials.py
pybdynamics/data_analysis/__init__.py
pybdynamics/data_analysis/cluster_analysis.py
pybdynamics/data_analysis/sys_params.py
pybdynamics/data_analysis/visualization.py
pybdynamics-0.0.2.dist-info/LICENSE
pybdynamics-0.0.2.dist-info/METADATA
pybdynamics-0.0.2.dist-info/WHEEL
pybdynamics-0.0.2.dist-info/top_level.txt
pybdynamics-0.0.2.dist-info/RECORD
