Metadata-Version: 2.1
Name: pybdynamics
Version: 0.0.2
Summary: Functions for BD simulations and data-analysis
Home-page: https://github.com/SalmanFarizN/packages/tree/master/pybdynamics
Author: Salman Fariz Navas
Author-email: salmanfarizn@gmail.com
License: MIT
Keywords: molecular dynamics,data analysis,brownian dynamics
License-File: LICENSE
Requires-Dist: numpy
Requires-Dist: numba
